<?xml version="1.0" encoding="UTF-8"?>
<root>	<sentences sloka="11.1">
		<sanskrit>XI. athaikādaśodhyāyaḥ.  (viśvarūpadarśanayogaḥ) arjuna uvāca madanugrahāya paramaṃ guhyam adhyātmasaṃjñitam yat tvayoktaṃ vacas tena mohoyaṃ vigato mama</sanskrit>
	</sentences>	<sentences sloka="11.2">
		<sanskrit>bhavāpyayau hi bhūtānāṃ śrutau vistaraśo mayā tvattaḥ kamalapatrākṣa māhātmyam api cāvyayam</sanskrit>
	</sentences>	<sentences sloka="11.3">
		<sanskrit>evam etad yathāttha tvam ātmānaṃ parameśvara draṣṭum icchāmi te rūpam aiśvaraṃ puruṣottama</sanskrit>
	</sentences>	<sentences sloka="11.4">
		<sanskrit>manyase yadi tac chakyaṃ mayā draṣṭum iti prabho yogeśvara tato me tvaṃ darśayātmānam avyayam</sanskrit>
	</sentences>	<sentences sloka="11.5">
		<sanskrit>śrībhagavān uvāca paśya me pārtha rūpāṇi śataśotha sahastraśaḥ nānāvidhāni divyāni nānāvarṇākṛtīni ca</sanskrit>
	</sentences>	<sentences sloka="11.6">
		<sanskrit>paśyādityān vasūn rudrān aśvinau marutas tathā bahūny adṛṣṭapūrvāṇi paśyāścaryāṇi bhārata</sanskrit>
	</sentences>	<sentences sloka="11.7">
		<sanskrit>ihaikasthaṃ jagat kṛtsnaṃ paśyādya sacarācaram mama dehe guḍākeśa yac cānyad draṣṭum icchasi</sanskrit>
	</sentences>	<sentences sloka="11.8">
		<sanskrit>na tu māṃ śakyase draṣṭum anenaiva svacakṣuṣā divyaṃ dadāmi te cakṣuḥ paśya me yogam aiśvaram</sanskrit>
	</sentences>	<sentences sloka="11.9">
		<sanskrit>sañjaya uvāca evam uktvā tato rājan mahāyogeśvaro hariḥ darśayām āsa pārthāya paramaṃ rūpam aiśvaram</sanskrit>
	</sentences>	<sentences sloka="11.10">
		<sanskrit>anekavaktranayanam anekādbhutadarśanam anekadivyābharaṇaṃ divyānekodyatāyudham</sanskrit>
	</sentences>	<sentences sloka="11.11">
		<sanskrit>divyamālyāmbaradharaṃ divyagandhānulepanam sarvāścaryamayaṃ devam anantaṃ viśvatomukham</sanskrit>
	</sentences>	<sentences sloka="11.12">
		<sanskrit>divi sūryasahastrasya bhaved yugapad utthitā yadi bhāḥ sadṛśī sā syād bhāsas tasya mahātmanaḥ</sanskrit>
	</sentences>	<sentences sloka="11.13">
		<sanskrit>tatraikasthaṃ jagat kṛtsnaṃ pravibhaktam anekadhā apaśyad devadevasya śarīre pāṇḍavas tadā</sanskrit>
	</sentences>	<sentences sloka="11.14">
		<sanskrit>tataḥ sa vismayāviṣṭo hṛṣṭaromā dhanaṃjayaḥ praṇamya śirasā devaṃ kṛtāñjalir abhāṣata</sanskrit>
	</sentences>	<sentences sloka="11.15">
		<sanskrit>arjuna uvāca paśyāmi devāṃs tava deva dehe sarvāṃs tathā bhūtaviśeṣasaṃghān brahmāṇam īśaṃ kamalāsanasthaṃ ṛṣīṃś ca sarvān uragāṃś ca divyān</sanskrit>
	</sentences>	<sentences sloka="11.16">
		<sanskrit>anekabāhūdaravaktranetraṃ paśyāmi tvāṃ sarvatonantarūpam nāntaṃ na madhyaṃ na punas tavādiṃ paśyāmi viśveśvara viśvarūpa</sanskrit>
	</sentences>	<sentences sloka="11.17">
		<sanskrit>kirīṭinaṃ gadinaṃ cakriṇaṃ ca tejorāśiṃ sarvato dīptimantam paśyāmi tvāṃ durnirīkṣyaṃ samantād dīptānalārkadyutim aprameyam</sanskrit>
	</sentences>	<sentences sloka="11.18">
		<sanskrit>tvam akṣaraṃ paramaṃ veditavyaṃ tvam asya viśvasya paraṃ nidhānam tvam avyayaḥ śāśvatadharmagoptā sanātanas tvaṃ puruṣo mato me</sanskrit>
	</sentences>	<sentences sloka="11.19">
		<sanskrit>anādimadhyāntam anantavīryam anantabāhuṃ śaśisūryanetram paśyāmi tvāṃ dīptahutāśavaktraṃ svatejasā viśvam idaṃ tapantam</sanskrit>
	</sentences>	<sentences sloka="11.20">
		<sanskrit>dyāvāpṛthivyor idam antaraṃ hi vyāptaṃ tvayaikena diśaś ca sarvāḥ dṛṣṭvādbhutaṃ rupam ugraṃ tavedaṃ lokatrayaṃ pravyathitaṃ mahātman</sanskrit>
	</sentences>	<sentences sloka="11.21">
		<sanskrit>amī hi tvāṃ surasaṃghā viśanti kecid bhītāḥ prāñjalayo gṛṇanti svastīty uktvā maharṣisiddhasaṃghāḥ stuvanti tvāṃ stutibhiḥ puṣkalābhiḥ</sanskrit>
	</sentences>	<sentences sloka="11.22">
		<sanskrit>rudrādityā vasavo ye ca sādhyā viśveśvinau marutaś coṣmapāś ca gandharvayakṣāsurasiddhasaṃghā vīkṣante tvāṃ vismitāś caiva sarve</sanskrit>
	</sentences>	<sentences sloka="11.23">
		<sanskrit>rūpaṃ mahat te bahuvaktranetraṃ mahābāho bahubāhūrupādam bahūdaraṃ bahudañṣṭrākarālaṃ dṛṣṭvā lokāḥ pravyathitās tathāham</sanskrit>
	</sentences>	<sentences sloka="11.24">
		<sanskrit>nabhaḥspṛśaṃ dīptam anekavarṇaṃ vyāttānanaṃ dīptaviśālanetram dṛṣṭvā hi tvāṃ pravyathitāntarātmā dhṛtiṃ na vindāmi śamaṃ ca viṣṇo</sanskrit>
	</sentences>	<sentences sloka="11.25">
		<sanskrit>daṃṣṭrākarālāni ca te mukhāni dṛṣṭvaiva kālānalasaṃnibhāni diśo na jāne na labhe ca śarma prasīda deveśa jagannivāsa</sanskrit>
	</sentences>	<sentences sloka="11.26">
		<sanskrit>amī ca tvāṃ dhṛtarāṣṭrasya putrāḥ sarve sahaivāvanipālasaṃghaiḥ bhīṣmo droṇaḥ sūtaputras tathāsau sahāsmadīyair api yodhamukhyaiḥ</sanskrit>
	</sentences>	<sentences sloka="11.27">
		<sanskrit>vaktrāṇi te tvaramāṇā viśanti daṃṣṭrākarālāni bhayānakāni kecid vilagnā daśanāntareṣu saṃdṛśyante cūrṇitair uttamāṅgaiḥ</sanskrit>
	</sentences>	<sentences sloka="11.28">
		<sanskrit>yathā nadīnāṃ bahavombuvegāḥ samudram evābhimukhā dravanti tathā tavāmī naralokavīrā viśanti vaktrāṇy abhivijvalanti</sanskrit>
	</sentences>	<sentences sloka="11.29">
		<sanskrit>yathā pradīptaṃ jvalanaṃ pataṅgā viśanti nāśāya samṛddhavegāḥ tathaiva nāśāya viśanti lokās tavāpi vaktrāṇi samṛddhavegāḥ</sanskrit>
	</sentences>	<sentences sloka="11.30">
		<sanskrit>lelihyase grasamānaḥ samantāl lokān samagrān vadanair jvaladbhiḥ tejobhir āpūrya jagat samagraṃ bhāsas tavogrāḥ pratapanti viṣṇo</sanskrit>
	</sentences>	<sentences sloka="11.31">
		<sanskrit>ākhyāhi me ko bhavān ugrarūpo namostu te devavara prasīda vijñātum icchāmi bhavantam ādyaṃ na hi prajānāmi tava pravṛttim</sanskrit>
	</sentences>	<sentences sloka="11.32">
		<sanskrit>śrībhagavān uvāca kālosmi lokakṣayakṛt pravṛddho lokān samāhartum iha pravṛttaḥ ṛtepi tvāṃ na bhaviṣyanti sarve yevasthitāḥ pratyanīkeṣu yodhāḥ</sanskrit>
	</sentences>	<sentences sloka="11.33">
		<sanskrit>tasmāt tvam uttiṣṭha yaśo labhasva jitvā śatrūn bhuṅkṣva rājyaṃ samṛddham mayaivaite nihatāḥ pūrvam eva nimittamātraṃ bhava savyasācin</sanskrit>
	</sentences>	<sentences sloka="11.34">
		<sanskrit>droṇaṃ ca bhīṣmaṃ ca jayadrathaṃ ca karṇaṃ tathānyān api yodhavīrān mayā hatāṃs tvaṃ jahi mā vyathiṣṭhā yudhyasva jetāsi raṇe sapatnān</sanskrit>
	</sentences>	<sentences sloka="11.35">
		<sanskrit>sañjaya uvāca etac chrutvā vacanaṃ keśavasya kṛtāñjalir vepamānaḥ kirīṭī namaskṛtvā bhūya evāha kṛṣṇaṃ sagadgadaṃ bhītabhītaḥ praṇamya</sanskrit>
	</sentences>	<sentences sloka="11.36">
		<sanskrit>arjuna uvāca sthāne hṛṣīkeśa tava prakīrtyā jagat prahṛṣyaty anurajyate ca rakṣāṃsi bhītāni diśo dravanti sarve namasyanti ca siddhasaṃghāḥ</sanskrit>
	</sentences>	<sentences sloka="11.37">
		<sanskrit>kasmāc ca te na nameran mahātman garīyase brahmaṇopy ādikartre ananta deveśa jagannivāsa tvam akṣaraṃ sad asat tatparaṃ yat</sanskrit>
	</sentences>	<sentences sloka="11.38">
		<sanskrit>tvam ādidevaḥ puruṣaḥ purāṇas tvam asya viśvasya paraṃ nidhānam vettāsi vedyaṃ ca paraṃ ca dhāma tvayā tataṃ viśvam anantarūpa</sanskrit>
	</sentences>	<sentences sloka="11.39">
		<sanskrit>vāyur yamognir varuṇaḥ śaśāṅkaḥ prajāpatis tvaṃ prapitāmahaś ca namo namas testu sahastrakṛtvaḥ punaś ca bhūyopi namo namas te</sanskrit>
	</sentences>	<sentences sloka="11.40">
		<sanskrit>namaḥ purastād atha pṛṣṭhatas te namostu te sarvata eva sarva anantavīryāmitavikramas tvaṃ sarvaṃ samāpnoṣi tatosi sarvaḥ</sanskrit>
	</sentences>	<sentences sloka="11.41">
		<sanskrit>sakheti matvā prasabhaṃ yad uktaṃ he kṛṣṇa he yādava he sakheti ajānatā mahimānaṃ tavedaṃ mayā pramādāt praṇayena vāpi</sanskrit>
	</sentences>	<sentences sloka="11.42">
		<sanskrit>yac cāvahāsārtham asatkṛtosi vihāraśayyāsanabhojaneṣu ekothavāpy acyuta tatsamakṣaṃ tat kṣāmaye tvām aham aprameyam</sanskrit>
	</sentences>	<sentences sloka="11.43">
		<sanskrit>pitāsi lokasya carācarasya tvam asya pūjyaś ca gurur garīyān na tvatsamosty abhyadhikaḥ kutonyo lokatrayepy apratimaprabhāva</sanskrit>
	</sentences>	<sentences sloka="11.44">
		<sanskrit>tasmāt praṇamya praṇidhāya kāyaṃ prasādaye tvām aham īśam īḍyam piteva putrasya sakheva sakhyuḥ priyaḥ priyāyārhasi deva soḍhum</sanskrit>
	</sentences>	<sentences sloka="11.45">
		<sanskrit>adṛṣṭapūrvaṃ hṛṣitosmi dṛṣṭvā bhayena ca pravyathitaṃ mano me tad eva me darśaya deva rūpaṃ prasīda deveśa jagannivāsa</sanskrit>
	</sentences>	<sentences sloka="11.46">
		<sanskrit>kirīṭinaṃ gadinaṃ cakrahastaṃ icchāmi tvāṃ draṣṭum ahaṃ tathaiva tenaiva rūpeṇa caturbhujena sahastrabāho bhava viśvamūrte</sanskrit>
	</sentences>	<sentences sloka="11.47">
		<sanskrit>śrībhagavān uvāca mayā prasannena tavārjunedaṃ rūpaṃ paraṃ darśitam ātmayogāt tejomayaṃ viśvam anantam ādyaṃ yan me tvadanyena na dṛṣṭapūrvam</sanskrit>
	</sentences>	<sentences sloka="11.48">
		<sanskrit>na veda yajñādhyayanair na dānaiḥ na ca kriyābhir na tapobhir ugraiḥ evaṃrūpaḥ śakya ahaṃ nṛloke draṣṭuṃ tvadanyena kurupravīra</sanskrit>
	</sentences>	<sentences sloka="11.49">
		<sanskrit>mā te vyathā mā ca vimūḍhabhāvo dṛṣṭvā rūpaṃ ghoram īdṛṅ mamedam vyapetabhīḥ prītamanāḥ punas tvaṃ tad eva me rūpam idaṃ prapaśya</sanskrit>
	</sentences>	<sentences sloka="11.50">
		<sanskrit>sañjaya uvāca ity arjunaṃ vāsudevas tathoktvā svakaṃ rūpaṃ darśayām āsa bhūyaḥ āśvāsayām āsa ca bhītam enaṃ bhūtvā punaḥ saumyavapur mahātmā</sanskrit>
	</sentences>	<sentences sloka="11.51">
		<sanskrit>arjuna uvāca dṛṣṭvedaṃ mānuṣaṃ rūpaṃ tava saumyaṃ janārdana idānīm asmi saṃvṛttaḥ sacetāḥ prakṛtiṃ gataḥ</sanskrit>
	</sentences>	<sentences sloka="11.52">
		<sanskrit>śrībhagavān uvāca sudurdarśam idaṃ rūpaṃ dṛṣṭvān asi yan mama devā apy asya rūpasya nityaṃ darśanakāṅkṣiṇaḥ</sanskrit>
	</sentences>	<sentences sloka="11.53">
		<sanskrit>nāhaṃ vedair na tapasā na dānena na cejyayā śakya evaṃvidho draṣṭuṃ dṛṣṭavān asi māṃ yathā</sanskrit>
	</sentences>	<sentences sloka="11.54">
		<sanskrit>bhaktyā tv ananyayā śakya aham evaṃvidhorjuna jñātuṃ draṣṭuṃ ca tattvena praveṣṭuṃ ca paraṃtapa</sanskrit>
	</sentences>	<sentences sloka="11.55">
		<sanskrit>matkarmakṛn matparamo madbhaktaḥ saṅgavarjitaḥ nirvairaḥ sarvabhūteṣu yaḥ sa mām eti pāṇḍava</sanskrit>
	</sentences></root>